cert_hero/__init__.py
cert_hero/__version__.py
cert_hero/cert_hero.py
cert_hero/cli.py
cert_hero-0.4.0.dist-info/LICENSE
cert_hero-0.4.0.dist-info/METADATA
cert_hero-0.4.0.dist-info/WHEEL
cert_hero-0.4.0.dist-info/entry_points.txt
cert_hero-0.4.0.dist-info/top_level.txt
cert_hero-0.4.0.dist-info/RECORD
