Metadata-Version: 2.1
Name: cert-hero
Version: 0.4.0
Summary: Python Stand-alone Library to Download the SSL Certificate for Any Host™
Home-page: https://github.com/rnag/cert-hero
Author: Ritvik Nag
Author-email: rv.kvetch@gmail.com
License: MIT
Project-URL: Documentation, https://cert-hero.readthedocs.io
Project-URL: Source, https://github.com/rnag/cert-hero
Keywords: cert-hero,cert,ssl,certificate,host cert
Platform: UNKNOWN
Classifier: Development Status :: 2 - Pre-Alpha
Classifier: Intended Audience :: Developers
Classifier: License :: OSI Approved :: MIT License
Classifier: Natural Language :: English
Classifier: Programming Language :: Python :: 3 :: Only
Classifier: Programming Language :: Python :: 3
Classifier: Programming Language :: Python :: 3.8
Classifier: Programming Language :: Python :: 3.9
Classifier: Programming Language :: Python :: 3.10
Classifier: Programming Language :: Python :: 3.11
Classifier: Programming Language :: Python :: 3.12
Classifier: Programming Language :: Python
Requires-Python: >=3.8
Requires-Dist: asn1crypto <2,>=1.5.1
Provides-Extra: dev
Requires-Dist: pip >=23.3 ; extra == 'dev'
Requires-Dist: bump2version ==1.0.1 ; extra == 'dev'
Requires-Dist: wheel ==0.41.2 ; extra == 'dev'
Requires-Dist: watchdog[watchmedo] ==3.0.0 ; extra == 'dev'
Requires-Dist: flake8 ==6.1.0 ; extra == 'dev'
Requires-Dist: tox ==4.11.3 ; extra == 'dev'
Requires-Dist: coverage ==7.3.2 ; extra == 'dev'
Requires-Dist: Sphinx <8,>=7.1.2 ; extra == 'dev'
Requires-Dist: twine ==4.0.2 ; extra == 'dev'
Requires-Dist: pytest ==7.4.2 ; extra == 'dev'
Requires-Dist: pytest-cov ==4.1.0 ; extra == 'dev'
Requires-Dist: pytest-runner ==6.0.0 ; extra == 'dev'
Requires-Dist: fake-useragent <2,>=1.0.0 ; extra == 'dev'
Provides-Extra: fake-ua
Requires-Dist: fake-useragent <2,>=1.0.0 ; extra == 'fake-ua'
